jimitsec-1.0.0.dist-info/RECORD
jimitsec-1.0.0.dist-info/top_level.txt
jimitsec-1.0.0.dist-info/WHEEL
jimitsec-1.0.0.dist-info/METADATA
jimitsec/security.cpython-37m-aarch64-linux-gnu.so
jimitsec/__init__.cpython-37m-aarch64-linux-gnu.so
