Metadata-Version: 2.1
Name: jimitsec
Version: 1.0.0
Summary: James Iter's security common library by python.
Home-page: https://github.com/jamesiter/jimitlib-py.git
Author: James Iter
Author-email: james.iter.cn@gmail.com
License: BSD
Platform: UNKNOWN
Classifier: Development Status :: 1 - Planning
Classifier: Environment :: Plugins
Classifier: Intended Audience :: Developers
Classifier: License :: OSI Approved :: BSD License
Classifier: Operating System :: POSIX :: Linux
Classifier: Programming Language :: Python
